compilelabs/__init__.py
compilelabs-0.0.1.dist-info/METADATA
compilelabs-0.0.1.dist-info/WHEEL
compilelabs-0.0.1.dist-info/licenses/LICENSE
compilelabs-0.0.1.dist-info/RECORD
